scielo_extractor/__init__.py
scielo_extractor/cli.py
scielo_extractor/extractor.py
scielo_extractor-0.0.6.dist-info/METADATA
scielo_extractor-0.0.6.dist-info/WHEEL
scielo_extractor-0.0.6.dist-info/entry_points.txt
scielo_extractor-0.0.6.dist-info/top_level.txt
scielo_extractor-0.0.6.dist-info/RECORD
