Metadata-Version: 2.1
Name: scielo-extractor
Version: 0.0.6
Summary: SciELO data extractor
Home-page: UNKNOWN
License: UNKNOWN
Keywords: data extraction,bibliographic data,scientific literature
Platform: UNKNOWN
Requires-Dist: requests
Requires-Dist: tqdm
Requires-Dist: xylose
Requires-Dist: pandas
Requires-Dist: lxml
